{
  "ac_unit": 61697,
  "access_alarm": 61698,
  "access_alarms": 61699,
  "access_time": 61700,
  "accessibility_new": 61701,
  "accessibility": 61702,
  "accessible_forward": 61703,
  "accessible": 61704,
  "account_balance_wallet": 61705,
  "account_balance": 61706,
  "account_box": 61707,
  "account_circle": 61708,
  "actions": 61709,
  "adb": 61710,
  "add_a_photo": 61711,
  "add_alarm": 61712,
  "add_box": 61713,
  "add_call": 61714,
  "add_circle_outline": 61715,
  "add_circle": 61716,
  "add_comment": 61717,
  "add_location": 61718,
  "add_photo_alternate": 61719,
  "add_shopping_cart": 61720,
  "add_to_home_screen": 61721,
  "add_to_photos": 61722,
  "add_to_queue": 61723,
  "add": 61724,
  "adjust": 61725,
  "admin": 61726,
  "ai_fabric": 61727,
  "airline_seat_flat_angled": 61728,
  "airline_seat_flat": 61729,
  "airline_seat_individual_suite": 61730,
  "airline_seat_legroom_extra": 61731,
  "airline_seat_legroom_normal": 61732,
  "airline_seat_legroom_reduced": 61733,
  "airline_seat_recline_extra": 61734,
  "airline_seat_recline_normal": 61735,
  "airplanemode_active": 61736,
  "airplanemode_inactive": 61737,
  "airplay": 61738,
  "airport_shuttle": 61739,
  "alarm_add": 61740,
  "alarm_off": 61741,
  "alarm_on": 61742,
  "alarm": 61743,
  "album": 61744,
  "alert_add": 61745,
  "alert_error_outline": 61746,
  "alert_error": 61747,
  "alert_notification_important": 61748,
  "alert_warning_amber": 61749,
  "alert_warning": 61750,
  "all_inbox": 61751,
  "all_inclusive": 61752,
  "all_out": 61753,
  "allocate_license": 61754,
  "alternate_email": 61755,
  "android": 61756,
  "announcement": 61757,
  "apps": 61758,
  "archive": 61759,
  "arrow_360": 61760,
  "arrow_back_ios": 61761,
  "arrow_back": 61762,
  "arrow_downward": 61763,
  "arrow_drop_down_circle": 61764,
  "arrow_drop_down": 61765,
  "arrow_drop_up": 61766,
  "arrow_forward_ios": 61767,
  "arrow_forward": 61768,
  "arrow_left": 61769,
  "arrow_right_alt": 61770,
  "arrow_right": 61771,
  "arrow_upward": 61772,
  "art_track": 61773,
  "aspect_ratio": 61774,
  "assessment": 61775,
  "assignment_ind": 61776,
  "assignment_late": 61777,
  "assignment_return": 61778,
  "assignment_returned": 61779,
  "assignment_turned_in": 61780,
  "assignment": 61781,
  "assistant_photo": 61782,
  "assistant": 61783,
  "atm": 61784,
  "attach_file": 61785,
  "attach_money": 61786,
  "attachment": 61787,
  "attribution": 61788,
  "audiotrack": 61789,
  "automation_hub": 61790,
  "autorenew": 61791,
  "backspace": 61792,
  "backup": 61793,
  "ballot": 61794,
  "bar_chart": 61795,
  "basic_auth_user": 61796,
  "battery_alert": 61797,
  "battery_charging_full": 61798,
  "battery_full": 61799,
  "battery_std": 61800,
  "battery_unknown": 61801,
  "beach_access": 61802,
  "beenhere": 61803,
  "block": 61804,
  "bluetooth_audio": 61805,
  "bluetooth_connected": 61806,
  "bluetooth_disabled": 61807,
  "bluetooth_searching": 61808,
  "bluetooth": 61809,
  "blur_circular": 61810,
  "blur_linear": 61811,
  "blur_off": 61812,
  "blur_on": 61813,
  "book": 61814,
  "bookmark_border": 61815,
  "bookmark": 61816,
  "bookmarks": 61817,
  "border_all": 61818,
  "border_bottom": 61819,
  "border_clear": 61820,
  "border_color": 61821,
  "border_horizontal": 61822,
  "border_inner": 61823,
  "border_left": 61824,
  "border_outer": 61825,
  "border_right": 61826,
  "border_style": 61827,
  "border_top": 61828,
  "border_vertical": 61829,
  "bottom-align": 61830,
  "branding_watermark": 61831,
  "brightness_1": 61832,
  "brightness_2": 61833,
  "brightness_3": 61834,
  "brightness_4": 61835,
  "brightness_5": 61836,
  "brightness_6": 61837,
  "brightness_7": 61838,
  "brightness_auto": 61839,
  "brightness_high": 61840,
  "brightness_low": 61841,
  "brightness_medium": 61842,
  "broken_image": 61843,
  "brush": 61844,
  "bubble_chart": 61845,
  "bug_report": 61846,
  "build": 61847,
  "burst_mode": 61848,
  "business_center": 61849,
  "business": 61850,
  "cached": 61851,
  "cake": 61852,
  "calendar_today": 61853,
  "calendar_view_day": 61854,
  "call_end": 61855,
  "call_made": 61856,
  "call_merge": 61857,
  "call_missed_outgoing": 61858,
  "call_missed": 61859,
  "call_received": 61860,
  "call_split": 61861,
  "call_to_action": 61862,
  "call": 61863,
  "camera_alt": 61864,
  "camera_enhance": 61865,
  "camera_front": 61866,
  "camera_rear": 61867,
  "camera_roll": 61868,
  "camera": 61869,
  "cancel_presentation": 61870,
  "cancel": 61871,
  "card_giftcard": 61872,
  "card_membership": 61873,
  "card_travel": 61874,
  "casino": 61875,
  "cast_connected": 61876,
  "cast_for_education": 61877,
  "cast": 61878,
  "category": 61879,
  "cell_wifi": 61880,
  "center_focus_strong": 61881,
  "center_focus_weak": 61882,
  "center-align": 61883,
  "change_history": 61884,
  "chat_bubble_outline": 61885,
  "chat_bubble": 61886,
  "chat": 61887,
  "chatbot": 61888,
  "check_box_outline_blank": 61889,
  "check_box": 61890,
  "check_circle_outline": 61891,
  "check_circle": 61892,
  "check": 61893,
  "chevron_left": 61894,
  "chevron_right": 61895,
  "child_care": 61896,
  "child_friendly": 61897,
  "chrome_reader_mode": 61898,
  "class": 61899,
  "clear_all": 61900,
  "clear": 61901,
  "close": 61902,
  "closed_caption": 61903,
  "cloud_circle": 61904,
  "cloud_done": 61905,
  "cloud_download": 61906,
  "cloud_off": 61907,
  "cloud_queue": 61908,
  "cloud_upload": 61909,
  "cloud": 61910,
  "code": 61911,
  "collections_bookmark": 61912,
  "collections": 61913,
  "color_lens": 61914,
  "colorize": 61915,
  "comment": 61916,
  "commute": 61917,
  "compare_arrows": 61918,
  "compare": 61919,
  "compass_calibration": 61920,
  "computer": 61921,
  "confirmation_number": 61922,
  "contact_mail": 61923,
  "contact_phone": 61924,
  "contact_support": 61925,
  "contacts": 61926,
  "control_camera": 61927,
  "control_point_duplicate": 61928,
  "control_point": 61929,
  "copy": 61930,
  "copyright": 61931,
  "create_new_folder": 61932,
  "create": 61933,
  "credit_card": 61934,
  "crop_16_9": 61935,
  "crop_3_2": 61936,
  "crop_5_4": 61937,
  "crop_7_5": 61938,
  "crop_din": 61939,
  "crop_free": 61940,
  "crop_landscape": 61941,
  "crop_original": 61942,
  "crop_portrait": 61943,
  "crop_rotate": 61944,
  "crop_square": 61945,
  "crop": 61946,
  "cut": 61947,
  "dashboard": 61948,
  "data_usage": 61949,
  "date_range": 61950,
  "dehaze": 61951,
  "delete_forever": 61952,
  "delete_outline": 61953,
  "delete_sweep": 61954,
  "delete": 61955,
  "departure_board": 61956,
  "description": 61957,
  "desktop_access_disabled": 61958,
  "desktop_mac": 61959,
  "desktop_windows": 61960,
  "details": 61961,
  "developer_board": 61962,
  "developer_mode": 61963,
  "device_hub": 61964,
  "device_unknown": 61965,
  "devices_other": 61966,
  "devices": 61967,
  "dialer_sip": 61968,
  "dialpad": 61969,
  "directions_bike": 61970,
  "directions_boat": 61971,
  "directions_bus": 61972,
  "directions_car": 61973,
  "directions_railway": 61974,
  "directions_run": 61975,
  "directions_subway": 61976,
  "directions_transit": 61977,
  "directions_walk": 61978,
  "directions": 61979,
  "directory_group": 61980,
  "directory_user": 61981,
  "disc_full": 61982,
  "dns": 61983,
  "do_disturb_alt": 61984,
  "do_disturb_off": 61985,
  "do_disturb_on": 61986,
  "do_disturb": 61987,
  "dock": 61988,
  "domain_disabled": 61989,
  "domain": 61990,
  "done_all": 61991,
  "done_outline": 61992,
  "done": 61993,
  "donut_large": 61994,
  "donut_small": 61995,
  "download_done": 61996,
  "download": 61997,
  "drafts": 61998,
  "drag_handle": 61999,
  "drag_indicator": 62000,
  "drive_eta": 62001,
  "duo": 62002,
  "dvr": 62003,
  "edit_attributes": 62004,
  "edit_location": 62005,
  "edit": 62006,
  "eject": 62007,
  "email": 62008,
  "enhanced_encryption": 62009,
  "entities": 62010,
  "equalizer": 62011,
  "euro_symbol": 62012,
  "ev_station": 62013,
  "event_available": 62014,
  "event_busy": 62015,
  "event_note": 62016,
  "event_seat": 62017,
  "event": 62018,
  "exit_to_app": 62019,
  "expand_less": 62020,
  "expand_more": 62021,
  "explicit": 62022,
  "explore_off": 62023,
  "explore": 62024,
  "exposure_neg_1": 62025,
  "exposure_neg_2": 62026,
  "exposure_plus_1": 62027,
  "exposure_plus_2": 62028,
  "exposure_zero": 62029,
  "exposure": 62030,
  "extension": 62031,
  "face_unlock": 62032,
  "face": 62033,
  "fast_forward": 62034,
  "fast_rewind": 62035,
  "fastfood": 62036,
  "favorite_border": 62037,
  "favorite": 62038,
  "featured_play_list": 62039,
  "featured_video": 62040,
  "feedback": 62041,
  "fiber_dvr": 62042,
  "fiber_manual_record": 62043,
  "fiber_new": 62044,
  "fiber_pin": 62045,
  "fiber_smart_record": 62046,
  "file_copy": 62047,
  "filter_1": 62048,
  "filter_2": 62049,
  "filter_3": 62050,
  "filter_4": 62051,
  "filter_5": 62052,
  "filter_6": 62053,
  "filter_7": 62054,
  "filter_8": 62055,
  "filter_9_plus": 62056,
  "filter_9": 62057,
  "filter_b_and_w": 62058,
  "filter_center_focus": 62059,
  "filter_drama": 62060,
  "filter_frames": 62061,
  "filter_hdr": 62062,
  "filter_list": 62063,
  "filter_none": 62064,
  "filter_tilt_shift": 62065,
  "filter_vintage": 62066,
  "filter": 62067,
  "find_in_page": 62068,
  "find_replace": 62069,
  "fingerprint": 62070,
  "first_page": 62071,
  "fitness_center": 62072,
  "flag": 62073,
  "flare": 62074,
  "flash_auto": 62075,
  "flash_off": 62076,
  "flash_on": 62077,
  "flight_land": 62078,
  "flight_takeoff": 62079,
  "flight": 62080,
  "flip_to_back": 62081,
  "flip_to_front": 62082,
  "flip": 62083,
  "folder_open": 62084,
  "folder_shared": 62085,
  "folder_special": 62086,
  "folder": 62087,
  "font_download": 62088,
  "format_align_center": 62089,
  "format_align_justify": 62090,
  "format_align_left": 62091,
  "format_align_right": 62092,
  "format_bold": 62093,
  "format_clear": 62094,
  "format_color_fill": 62095,
  "format_color_reset": 62096,
  "format_color_text": 62097,
  "format_indent_decrease": 62098,
  "format_indent_increase": 62099,
  "format_italic": 62100,
  "format_line_spacing": 62101,
  "format_list_bulleted": 62102,
  "format_list_numbered_rtl": 62103,
  "format_list_numbered": 62104,
  "format_paint": 62105,
  "format_quote": 62106,
  "format_shapes": 62107,
  "format_size": 62108,
  "format_strikethrough": 62109,
  "format_textdirection_l_to_r": 62110,
  "format_textdirection_r_to_l": 62111,
  "format_underlined": 62112,
  "forum": 62113,
  "forward_10": 62114,
  "forward_30": 62115,
  "forward_5": 62116,
  "forward": 62117,
  "free_breakfast": 62118,
  "fullscreen_exit": 62119,
  "fullscreen": 62120,
  "functions": 62121,
  "g_translate": 62122,
  "gamepad": 62123,
  "games": 62124,
  "gavel": 62125,
  "gesture": 62126,
  "get_app": 62127,
  "gif": 62128,
  "golf_course": 62129,
  "gps_fixed": 62130,
  "gps_not_fixed": 62131,
  "gps_off": 62132,
  "grade": 62133,
  "gradient": 62134,
  "grain": 62135,
  "graph_device": 62136,
  "grid_off": 62137,
  "grid_on": 62138,
  "group_add": 62139,
  "group_work": 62140,
  "group": 62141,
  "hd": 62142,
  "hdr_off": 62143,
  "hdr_on": 62144,
  "hdr_strong": 62145,
  "hdr_weak": 62146,
  "headset_mic": 62147,
  "headset": 62148,
  "healing": 62149,
  "hearing": 62150,
  "help_outline": 62151,
  "help": 62152,
  "high_quality": 62153,
  "highlight_off": 62154,
  "highlight": 62155,
  "history": 62156,
  "home_2": 62157,
  "home": 62158,
  "horizontal_split": 62159,
  "hot_tub": 62160,
  "hotel": 62161,
  "hourglass_empty": 62162,
  "hourglass_full": 62163,
  "how_to_reg": 62164,
  "how_to_vote": 62165,
  "http": 62166,
  "https": 62167,
  "image_aspect_ratio": 62168,
  "image_search": 62169,
  "image": 62170,
  "import_contacts": 62171,
  "import_export": 62172,
  "important_devices": 62173,
  "inbox": 62174,
  "indeterminate_check_box": 62175,
  "info_2": 62176,
  "info": 62177,
  "input": 62178,
  "insert_chart_outlined": 62179,
  "insert_chart": 62180,
  "insert_comment": 62181,
  "insert_drive_file": 62182,
  "insert_emoticon": 62183,
  "insert_invitation": 62184,
  "insert_link": 62185,
  "insert_photo": 62186,
  "insights": 62187,
  "invert_colors_off": 62188,
  "invert_colors": 62189,
  "iso": 62190,
  "keyboard_arrow_down": 62191,
  "keyboard_arrow_left": 62192,
  "keyboard_arrow_right": 62193,
  "keyboard_arrow_up": 62194,
  "keyboard_backspace": 62195,
  "keyboard_capslock": 62196,
  "keyboard_hide": 62197,
  "keyboard_return": 62198,
  "keyboard_tab": 62199,
  "keyboard_voice": 62200,
  "keyboard": 62201,
  "kitchen": 62202,
  "label_2": 62203,
  "label_important_2": 62204,
  "label_important": 62205,
  "label_off": 62206,
  "label": 62207,
  "landscape": 62208,
  "language": 62209,
  "laptop_chromebook": 62210,
  "laptop_mac": 62211,
  "laptop_windows": 62212,
  "laptop": 62213,
  "last_page": 62214,
  "launch": 62215,
  "layers_clear": 62216,
  "layers": 62217,
  "leak_add": 62218,
  "leak_remove": 62219,
  "leftAlign": 62220,
  "lens": 62221,
  "library_add": 62222,
  "library_books": 62223,
  "library_music": 62224,
  "lightbulb": 62225,
  "line_style": 62226,
  "line_weight": 62227,
  "linear_scale": 62228,
  "link_off": 62229,
  "link": 62230,
  "linked_camera": 62231,
  "list_alt": 62232,
  "list": 62233,
  "live_help": 62234,
  "live_tv": 62235,
  "local_activity": 62236,
  "local_airport": 62237,
  "local_atm": 62238,
  "local_bar": 62239,
  "local_cafe": 62240,
  "local_car_wash": 62241,
  "local_convenience_store": 62242,
  "local_dining": 62243,
  "local_drink": 62244,
  "local_florist": 62245,
  "local_gas_station": 62246,
  "local_grocery_store": 62247,
  "local_group": 62248,
  "local_hospital": 62249,
  "local_hotel": 62250,
  "local_laundry_service": 62251,
  "local_library": 62252,
  "local_mall": 62253,
  "local_movies": 62254,
  "local_offer": 62255,
  "local_parking": 62256,
  "local_pharmacy": 62257,
  "local_phone": 62258,
  "local_pizza": 62259,
  "local_play": 62260,
  "local_post_office": 62261,
  "local_printshop": 62262,
  "local_see": 62263,
  "local_shipping": 62264,
  "local_taxi": 62265,
  "location_city": 62266,
  "location_disabled": 62267,
  "location_off": 62268,
  "location_on": 62269,
  "location_searching": 62270,
  "lock_2": 62271,
  "lock_open": 62272,
  "lock": 62273,
  "logout_custom_alt": 62274,
  "logout_custom": 62275,
  "looks_3": 62276,
  "looks_4": 62277,
  "looks_5": 62278,
  "looks_6": 62279,
  "looks_one": 62280,
  "looks_two": 62281,
  "looks": 62282,
  "loop": 62283,
  "loupe": 62284,
  "low_priority": 62285,
  "loyalty": 62286,
  "mail_outline": 62287,
  "mail": 62288,
  "map": 62289,
  "marketplace": 62290,
  "markunread_mailbox": 62291,
  "markunread": 62292,
  "maximize": 62293,
  "meeting_room": 62294,
  "memory": 62295,
  "menu": 62296,
  "merge_type": 62297,
  "message": 62298,
  "mic_none": 62299,
  "mic_off": 62300,
  "mic": 62301,
  "middleAlign": 62302,
  "minimize": 62303,
  "missed_video_call": 62304,
  "mms": 62305,
  "mobile_friendly": 62306,
  "mobile_off": 62307,
  "mobile_screen_share": 62308,
  "mode_comment": 62309,
  "mode": 62310,
  "monetization_on": 62311,
  "money_off_csred": 62312,
  "money_off": 62313,
  "money": 62314,
  "monochrome_photos": 62315,
  "mood_bad": 62316,
  "mood": 62317,
  "more_horiz": 62318,
  "more_kebab": 62319,
  "more_vert": 62320,
  "more": 62321,
  "motorcycle": 62322,
  "mouse": 62323,
  "move_to_inbox": 62324,
  "movie_creation": 62325,
  "movie_filter": 62326,
  "movie": 62327,
  "multiline_chart": 62328,
  "music_note": 62329,
  "music_off": 62330,
  "music_video": 62331,
  "my_location": 62332,
  "nature_people": 62333,
  "nature": 62334,
  "navigate_before": 62335,
  "navigate_next": 62336,
  "navigation": 62337,
  "near_me": 62338,
  "network_cell": 62339,
  "network_check": 62340,
  "network_locked": 62341,
  "network_wifi": 62342,
  "new_releases": 62343,
  "next_week": 62344,
  "nfc": 62345,
  "no_encryption_gmailerrorred": 62346,
  "no_encryption": 62347,
  "no_meeting_room": 62348,
  "no_sim": 62349,
  "not_interested": 62350,
  "not_listed_location": 62351,
  "note_add": 62352,
  "note": 62353,
  "notes": 62354,
  "notifications_active": 62355,
  "notifications_none": 62356,
  "notifications_off": 62357,
  "notifications_paused": 62358,
  "notifications": 62359,
  "offline_bolt": 62360,
  "offline_pin": 62361,
  "ondemand_video": 62362,
  "opacity": 62363,
  "open_in_browser": 62364,
  "open_in_new": 62365,
  "open_with": 62366,
  "orchestrator": 62367,
  "outlined_flag": 62368,
  "pages": 62369,
  "pageview": 62370,
  "palette": 62371,
  "pan_tool": 62372,
  "panorama_fish_eye": 62373,
  "panorama_horizontal": 62374,
  "panorama_vertical": 62375,
  "panorama_wide_angle": 62376,
  "panorama": 62377,
  "party_mode": 62378,
  "paste": 62379,
  "pause_circle_filled": 62380,
  "pause_circle_outline": 62381,
  "pause_presentation": 62382,
  "pause": 62383,
  "payment": 62384,
  "people_outline": 62385,
  "people": 62386,
  "perm_camera_mic": 62387,
  "perm_contact_calendar": 62388,
  "perm_data_setting": 62389,
  "perm_device_information": 62390,
  "perm_identity": 62391,
  "perm_media": 62392,
  "perm_phone_msg": 62393,
  "perm_scan_wifi": 62394,
  "person_add_disabled": 62395,
  "person_add": 62396,
  "person_outline": 62397,
  "person_pin_circle": 62398,
  "person_pin": 62399,
  "person": 62400,
  "personal_video": 62401,
  "pets": 62402,
  "phone_android": 62403,
  "phone_bluetooth_speaker": 62404,
  "phone_callback": 62405,
  "phone_forwarded": 62406,
  "phone_in_talk": 62407,
  "phone_iphone": 62408,
  "phone_locked": 62409,
  "phone_missed": 62410,
  "phone_paused": 62411,
  "phone": 62412,
  "phonelink_erase": 62413,
  "phonelink_lock": 62414,
  "phonelink_off": 62415,
  "phonelink_ring": 62416,
  "phonelink_setup": 62417,
  "phonelink": 62418,
  "photo_album": 62419,
  "photo_camera": 62420,
  "photo_filter": 62421,
  "photo_library": 62422,
  "photo_size_select_actual": 62423,
  "photo_size_select_large": 62424,
  "photo_size_select_small": 62425,
  "photo": 62426,
  "picture_as_pdf": 62427,
  "picture_in_picture_alt": 62428,
  "picture_in_picture": 62429,
  "pie_chart_outline": 62430,
  "pie_chart": 62431,
  "pin_drop": 62432,
  "place": 62433,
  "placeholder": 62434,
  "play_arrow": 62435,
  "play_circle_filled_white": 62436,
  "play_circle_filled": 62437,
  "play_circle_outline": 62438,
  "play_for_work": 62439,
  "playlist_add_check": 62440,
  "playlist_add": 62441,
  "playlist_play": 62442,
  "plus_one": 62443,
  "poll": 62444,
  "polymer": 62445,
  "pool": 62446,
  "portable_wifi_off": 62447,
  "portrait": 62448,
  "power_input": 62449,
  "power_off": 62450,
  "power_settings_new": 62451,
  "power": 62452,
  "pregnant_woman": 62453,
  "present_to_all": 62454,
  "print_disabled": 62455,
  "print": 62456,
  "priority_high": 62457,
  "processes": 62458,
  "public": 62459,
  "publish_2": 62460,
  "publish": 62461,
  "query_builder": 62462,
  "question_answer": 62463,
  "queue_music": 62464,
  "queue_play_next": 62465,
  "queue": 62466,
  "radio_button_checked": 62467,
  "radio_button_unchecked": 62468,
  "radio": 62469,
  "rate_review": 62470,
  "receipt": 62471,
  "recent_actors": 62472,
  "record_voice_over": 62473,
  "rectangle_136": 62474,
  "rectangle_137": 62475,
  "redeem": 62476,
  "redo": 62477,
  "refresh": 62478,
  "remove_circle_outline": 62479,
  "remove_circle": 62480,
  "remove_from_queue": 62481,
  "remove_red_eye": 62482,
  "remove_shopping_cart": 62483,
  "remove": 62484,
  "reorder": 62485,
  "repeat_one": 62486,
  "repeat": 62487,
  "replay_10": 62488,
  "replay_30": 62489,
  "replay_5": 62490,
  "replay": 62491,
  "reply_all": 62492,
  "reply": 62493,
  "report_gmailerrorred": 62494,
  "report_off": 62495,
  "report_problem": 62496,
  "report": 62497,
  "resolution_4k": 62498,
  "resource_center": 62499,
  "restaurant_menu": 62500,
  "restaurant": 62501,
  "restore_from_trash": 62502,
  "restore_page": 62503,
  "restore": 62504,
  "rightAlign": 62505,
  "ring_volume": 62506,
  "robot": 62507,
  "room_service": 62508,
  "room": 62509,
  "rotate_90_degrees_ccw": 62510,
  "rotate_left": 62511,
  "rotate_right": 62512,
  "rotation_3d": 62513,
  "rounded_corner": 62514,
  "router": 62515,
  "rowing": 62516,
  "rss_feed": 62517,
  "rv_hookup-1": 62518,
  "rv_hookup": 62519,
  "satellite": 62520,
  "save_alt": 62521,
  "save": 62522,
  "scanner": 62523,
  "scatter_plot": 62524,
  "schedule": 62525,
  "school": 62526,
  "score": 62527,
  "screen_lock_landscape": 62528,
  "screen_lock_portrait": 62529,
  "screen_lock_rotation": 62530,
  "screen_rotation": 62531,
  "screen_share": 62532,
  "sd_card_alert": 62533,
  "sd_card": 62534,
  "sd_storage": 62535,
  "search": 62536,
  "security": 62537,
  "select_all": 62538,
  "send": 62539,
  "sentiment_dissatisfied": 62540,
  "sentiment_neutral": 62541,
  "sentiment_satisfied_alt": 62542,
  "sentiment_satisfied": 62543,
  "sentiment_very_dissatisfied": 62544,
  "sentiment_very_satisfied": 62545,
  "settings_applications": 62546,
  "settings_backup_restore": 62547,
  "settings_bluetooth": 62548,
  "settings_brightness": 62549,
  "settings_cell": 62550,
  "settings_ethernet": 62551,
  "settings_input_antenna": 62552,
  "settings_input_component": 62553,
  "settings_input_composite": 62554,
  "settings_input_hdmi": 62555,
  "settings_input_svideo": 62556,
  "settings_overscan": 62557,
  "settings_phone": 62558,
  "settings_power": 62559,
  "settings_remote": 62560,
  "settings_system_daydream": 62561,
  "settings_voice": 62562,
  "settings": 62563,
  "share": 62564,
  "shop_two": 62565,
  "shop": 62566,
  "shopping_basket": 62567,
  "shopping_cart": 62568,
  "short_text": 62569,
  "show_chart": 62570,
  "shuffle": 62571,
  "shutter_speed": 62572,
  "signal_cellular_alt": 62573,
  "signal_cellular_connected_no_internet_4_bar": 62574,
  "signal_cellular_no_sim": 62575,
  "signal_cellular_null": 62576,
  "signal_cellular_off": 62577,
  "signal_wifi_off": 62578,
  "signal_wifi_statusbar_connected_no_internet": 62579,
  "signal_wifi_statusbar_not_connected": 62580,
  "signal_wifi_statusbar_null": 62581,
  "sim_card": 62582,
  "skip_next": 62583,
  "skip_previous": 62584,
  "slideshow": 62585,
  "slow_motion_video": 62586,
  "smartphone": 62587,
  "smoke_free": 62588,
  "smoking_rooms": 62589,
  "sms_failed": 62590,
  "sms": 62591,
  "snooze": 62592,
  "sort_by_alpha": 62593,
  "sort": 62594,
  "spa": 62595,
  "space_bar": 62596,
  "speaker_group": 62597,
  "speaker_notes_off": 62598,
  "speaker_notes": 62599,
  "speaker_phone": 62600,
  "speaker": 62601,
  "spellcheck": 62602,
  "star_border_purple500": 62603,
  "star_border": 62604,
  "star_half": 62605,
  "star_outline": 62606,
  "star_purple500": 62607,
  "star_rate": 62608,
  "star": 62609,
  "stars": 62610,
  "stay_current_landscape": 62611,
  "stay_current_portrait": 62612,
  "stay_primary_landscape": 62613,
  "stay_primary_portrait": 62614,
  "stop_screen_share": 62615,
  "stop": 62616,
  "storage": 62617,
  "store_mall_directory": 62618,
  "store": 62619,
  "straighten": 62620,
  "streetview": 62621,
  "strikethrough_s": 62622,
  "style": 62623,
  "subdirectory_arrow_left": 62624,
  "subdirectory_arrow_right": 62625,
  "subject": 62626,
  "subscriptions": 62627,
  "subtitles": 62628,
  "subway": 62629,
  "supervised_user_circle": 62630,
  "supervisor_account": 62631,
  "surround_sound": 62632,
  "swap_calls": 62633,
  "swap_horiz": 62634,
  "swap_horizontal_circle": 62635,
  "swap_vert": 62636,
  "swap_vertical_circle": 62637,
  "switch_camera": 62638,
  "switch_video": 62639,
  "sync_disabled": 62640,
  "sync_problem": 62641,
  "sync": 62642,
  "system_update": 62643,
  "system_vertical_alt": 62644,
  "tab_unselected": 62645,
  "tab": 62646,
  "table_chart": 62647,
  "tablet_android": 62648,
  "tablet_mac": 62649,
  "tablet": 62650,
  "tag_faces": 62651,
  "tap_and_play": 62652,
  "task_mining": 62653,
  "terrain": 62654,
  "test_manager": 62655,
  "text_fields": 62656,
  "text_format": 62657,
  "text_rotate_up": 62658,
  "text_rotate_vertical": 62659,
  "text_rotation_angle_down": 62660,
  "text_rotation_angle_up": 62661,
  "text_rotation_down": 62662,
  "text_rotation_none": 62663,
  "textsms": 62664,
  "texture": 62665,
  "theaters": 62666,
  "thermostat": 62667,
  "thumb_down_alt": 62668,
  "thumb_down": 62669,
  "thumb_up_alt": 62670,
  "thumb_up": 62671,
  "thumbs_up_down": 62672,
  "time_to_leave": 62673,
  "timelapse": 62674,
  "timeline": 62675,
  "timer_10": 62676,
  "timer_3": 62677,
  "timer_off": 62678,
  "timer-1": 62679,
  "timer": 62680,
  "title": 62681,
  "toc": 62682,
  "today": 62683,
  "toggle_off": 62684,
  "toggle_on": 62685,
  "toll": 62686,
  "tonality": 62687,
  "topAlign": 62688,
  "touch_app": 62689,
  "toys": 62690,
  "track_changes": 62691,
  "traffic": 62692,
  "train": 62693,
  "tram": 62694,
  "transfer_within_a_station": 62695,
  "transform": 62696,
  "transit_enterexit": 62697,
  "translate": 62698,
  "trending_down": 62699,
  "trending_flat": 62700,
  "trending_up": 62701,
  "trip_origin": 62702,
  "tune": 62703,
  "turned_in_not": 62704,
  "turned_in": 62705,
  "tv_off": 62706,
  "tv": 62707,
  "unarchive": 62708,
  "undo": 62709,
  "unfold_less": 62710,
  "unfold_more": 62711,
  "unsubscribe": 62712,
  "update": 62713,
  "upload": 62714,
  "usb": 62715,
  "user_avatar": 62716,
  "user_sso": 62717,
  "verified_user": 62718,
  "vertical_align_bottom": 62719,
  "vertical_align_center": 62720,
  "vertical_align_top": 62721,
  "vertical_split": 62722,
  "vibration": 62723,
  "video_call": 62724,
  "video_label": 62725,
  "video_library": 62726,
  "videocam_off": 62727,
  "videocam": 62728,
  "videogame_asset": 62729,
  "view_agenda": 62730,
  "view_array": 62731,
  "view_carousel": 62732,
  "view_column": 62733,
  "view_comfy": 62734,
  "view_compact": 62735,
  "view_day": 62736,
  "view_headline": 62737,
  "view_list": 62738,
  "view_module": 62739,
  "view_quilt": 62740,
  "view_stream": 62741,
  "view_week": 62742,
  "vignette": 62743,
  "visibility_off": 62744,
  "visibility": 62745,
  "voice_chat": 62746,
  "voice_over_off": 62747,
  "voicemail": 62748,
  "volume_down": 62749,
  "volume_mute": 62750,
  "volume_off": 62751,
  "volume_up": 62752,
  "vpn_key": 62753,
  "vpn_lock": 62754,
  "waffle": 62755,
  "wallpaper": 62756,
  "watch_later": 62757,
  "watch": 62758,
  "waves": 62759,
  "wb_auto": 62760,
  "wb_cloudy": 62761,
  "wb_incandescent": 62762,
  "wb_iridescent": 62763,
  "wb_sunny": 62764,
  "wc": 62765,
  "web_asset": 62766,
  "web": 62767,
  "weekend": 62768,
  "whatshot": 62769,
  "where_to_vote": 62770,
  "widgets": 62771,
  "wifi_lock": 62772,
  "wifi_off": 62773,
  "wifi_tethering": 62774,
  "wifi": 62775,
  "work_off": 62776,
  "work_outline": 62777,
  "work": 62778,
  "wrap_text": 62779,
  "youtube_searched_for": 62780,
  "zoom_in": 62781,
  "zoom_out_map": 62782,
  "zoom_out": 62783
}
